ipython2cwl/__init__.py
ipython2cwl/cwltoolextractor.py
ipython2cwl/iotypes.py
ipython2cwl/repo2cwl.py
ipython2cwl/requirements_manager.py
ipython2cwl/templates/template.dockerfile
ipython2cwl/templates/template.setup
ipython2cwl-0.0.4.dist-info/LICENSE
ipython2cwl-0.0.4.dist-info/METADATA
ipython2cwl-0.0.4.dist-info/WHEEL
ipython2cwl-0.0.4.dist-info/entry_points.txt
ipython2cwl-0.0.4.dist-info/top_level.txt
ipython2cwl-0.0.4.dist-info/RECORD
