Metadata-Version: 2.1
Name: ipython2cwl
Version: 0.0.4
Summary: Convert IPython Jupyter Notebooks to CWL tool
Home-page: https://ipython2cwl.readthedocs.io/
Author: Yannis Doukas
Author-email: giannisdoukas2311@gmail.com
License: UNKNOWN
Platform: UNKNOWN
Classifier: Development Status :: 3 - Alpha
Classifier: Environment :: Console
Classifier: Framework :: IPython
Classifier: Intended Audience :: Developers
Classifier: Intended Audience :: Science/Research
Classifier: License :: OSI Approved :: Apache Software License
Classifier: Operating System :: MacOS
Classifier: Operating System :: POSIX
Classifier: Programming Language :: Python :: 3
Classifier: Programming Language :: Python :: 3.6
Classifier: Programming Language :: Python :: 3.7
Classifier: Programming Language :: Python :: 3.8
Classifier: Topic :: Scientific/Engineering
Classifier: Topic :: Scientific/Engineering :: Astronomy
Classifier: Topic :: Scientific/Engineering :: Atmospheric Science
Classifier: Topic :: Scientific/Engineering :: Bio-Informatics
Classifier: Topic :: Scientific/Engineering :: Information Analysis
Classifier: Topic :: Scientific/Engineering :: Medical Science Apps.
Requires-Python: >=3.6
Requires-Dist: nbformat (>=5.0.6)
Requires-Dist: astor (>=0.8.1)
Requires-Dist: PyYAML (>=5.3.1)
Requires-Dist: gitpython (>=3.1.3)
Requires-Dist: jupyter-repo2docker (>=0.11.0)
Requires-Dist: nbconvert (==5.6.1)
Requires-Dist: ipython (>=7.15.0)
